tarxemo_django_graphene_utils/__init__.py
tarxemo_django_graphene_utils/types.py
tarxemo_django_graphene_utils/utils.py
tarxemo_django_graphene_utils-0.1.3.dist-info/licenses/LICENSE
tarxemo_django_graphene_utils-0.1.3.dist-info/METADATA
tarxemo_django_graphene_utils-0.1.3.dist-info/WHEEL
tarxemo_django_graphene_utils-0.1.3.dist-info/top_level.txt
tarxemo_django_graphene_utils-0.1.3.dist-info/RECORD
