Metadata-Version: 2.4
Name: tarxemo-django-graphene-utils
Version: 0.1.3
Summary: Shared Django Graphene utilities and DTOs for efficient API development
Home-page: https://github.com/tarxemo/tarxemo-django-graphene-utils
Author: TarXemo
Project-URL: Homepage, https://github.com/tarxemo/tarxemo-django-graphene-utils
Project-URL: Bug Tracker, https://github.com/tarxemo/tarxemo-django-graphene-utils/issues
Classifier: Framework :: Django
Classifier: Programming Language :: Python :: 3
Classifier: License :: OSI Approved :: MIT License
Classifier: Operating System :: OS Independent
Requires-Python: >=3.6
License-File: LICENSE
Requires-Dist: Django
Requires-Dist: graphene-django
Requires-Dist: graphene
Requires-Dist: graphql-core
Dynamic: home-page
Dynamic: license-file
Dynamic: requires-python
